Metadata-Version: 2.1
Name: adobe-analytic-API-V2.0-azure
Version: 0.0.3
Summary: Automate Adobe Analytics Reports API v2 requests to export to Azure Blob Storage programmatically.
Home-page: https://github.com/alexcargf/adobe_analytic-azure
Download-URL: https://github.com/alexcargf/adobe_analytic-azure/archive/refs/tags/0.0.3.tar.gz
Author: AlexZ
Author-email: alexdataanalyst@gmail.com
License: UNKNOWN
Platform: UNKNOWN
Classifier: Programming Language :: Python :: 3
Classifier: Programming Language :: Python :: 3.4
Classifier: Programming Language :: Python :: 3.5
Classifier: Programming Language :: Python :: 3.6
Classifier: License :: OSI Approved :: MIT License
Classifier: Operating System :: OS Independent
Requires-Python: >=3.6
